{"meta": {"last_updated_at": "2023-02-23T23:59:59Z"}, "data": {"ADA": {"code": "ADA", "value": 2.764911}, "AED": {"code": "AED", "value": 3.89285}, "AFN": {"code": "AFN", "value": 93.794688}, "ALL": {"code": "ALL", "value": 115.074937}, "AMD": {"code": "AMD", "value": 413.417166}, "ANG": {"code": "ANG", "value": 1.909642}, "AOA": {"code": "AOA", "value": 533.97338}, "ARS": {"code": "ARS", "value": 206.991956}, "AUD": {"code": "AUD", "value": 1.556457}, "AVAX": {"code": "AVAX", "value": 0.053746}, "AWG": {"code": "AWG", "value": 1.907687}, "AZN": {"code": "AZN", "value": 1.801705}, "BAM": {"code": "BAM", "value": 1.954386}, "BBD": {"code": "BBD", "value": 2.139468}, "BDT": {"code": "BDT", "value": 113.453757}, "BGN": {"code": "BGN", "value": 1.955698}, "BHD": {"code": "BHD", "value": 0.399561}, "BIF": {"code": "BIF", "value": 2188.542177}, "BMD": {"code": "BMD", "value": 1.059826}, "BNB": {"code": "BNB", "value": 0.003426}, "BND": {"code": "BND", "value": 1.422448}, "BOB": {"code": "BOB", "value": 7.321813}, "BRL": {"code": "BRL", "value": 5.445069}, "BSD": {"code": "BSD", "value": 1.059592}, "BTC": {"code": "BTC", "value": 4.4e-05}, "BTN": {"code": "BTN", "value": 87.656786}, "BWP": {"code": "BWP", "value": 14.071999}, "BYN": {"code": "BYN", "value": 2.674622}, "BYR": {"code": "BYR", "value": 20772.570033}, "BZD": {"code": "BZD", "value": 2.135872}, "CAD": {"code": "CAD", "value": 1.435349}, "CDF": {"code": "CDF", "value": 2168.934346}, "CHF": {"code": "CHF", "value": 0.989597}, "CLF": {"code": "CLF", "value": 0.030893}, "CLP": {"code": "CLP", "value": 852.418953}, "CNY": {"code": "CNY", "value": 7.32139}, "COP": {"code": "COP", "value": 5168.530456}, "CRC": {"code": "CRC", "value": 591.179328}, "CUC": {"code": "CUC", "value": 1.065076}, "CUP": {"code": "CUP", "value": 25.430893}, "CVE": {"code": "CVE", "value": 110.18351}, "CZK": {"code": "CZK", "value": 23.658286}, "DJF": {"code": "DJF", "value": 188.352294}, "DKK": {"code": "DKK", "value": 7.445327}, "DOP": {"code": "DOP", "value": 59.068318}, "DOT": {"code": "DOT", "value": 0.149144}, "DZD": {"code": "DZD", "value": 145.222765}, "EGP": {"code": "EGP", "value": 32.461211}, "ERN": {"code": "ERN", "value": 15.897402}, "ETB": {"code": "ETB", "value": 56.975887}, "ETH": {"code": "ETH", "value": 0.000641}, "EUR": {"code": "EUR", "value": 1}, "FJD": {"code": "FJD", "value": 2.336546}, "FKP": {"code": "FKP", "value": 0.88183}, "GBP": {"code": "GBP", "value": 0.881946}, "GEL": {"code": "GEL", "value": 2.792644}, "GGP": {"code": "GGP", "value": 0.881828}, "GHS": {"code": "GHS", "value": 13.669102}, "GIP": {"code": "GIP", "value": 0.88183}, "GMD": {"code": "GMD", "value": 64.755383}, "GNF": {"code": "GNF", "value": 9113.765358}, "GTQ": {"code": "GTQ", "value": 8.275486}, "GYD": {"code": "GYD", "value": 223.584799}, "HKD": {"code": "HKD", "value": 8.316622}, "HNL": {"code": "HNL", "value": 26.123679}, "HTG": {"code": "HTG", "value": 158.177044}, "HUF": {"code": "HUF", "value": 381.044928}, "IDR": {"code": "IDR", "value": 16127.903476}, "ILS": {"code": "ILS", "value": 3.845317}, "IMP": {"code": "IMP", "value": 0.881828}, "INR": {"code": "INR", "value": 87.560943}, "IQD": {"code": "IQD", "value": 1546.537225}, "IRR": {"code": "IRR", "value": 44883.651065}, "ISK": {"code": "ISK", "value": 152.678594}, "JEP": {"code": "JEP", "value": 0.88183}, "JMD": {"code": "JMD", "value": 163.484089}, "JOD": {"code": "JOD", "value": 0.751841}, "JPY": {"code": "JPY", "value": 142.689767}, "KES": {"code": "KES", "value": 133.834962}, "KGS": {"code": "KGS", "value": 92.650021}, "KHR": {"code": "KHR", "value": 4295.723061}, "KMF": {"code": "KMF", "value": 490.540702}, "KPW": {"code": "KPW", "value": 953.858772}, "KRW": {"code": "KRW", "value": 1376.110168}, "KWD": {"code": "KWD", "value": 0.325208}, "KYD": {"code": "KYD", "value": 0.883047}, "KZT": {"code": "KZT", "value": 475.028762}, "LAK": {"code": "LAK", "value": 17869.498516}, "LBP": {"code": "LBP", "value": 15941.658641}, "LKR": {"code": "LKR", "value": 386.762173}, "LRD": {"code": "LRD", "value": 167.240676}, "LSL": {"code": "LSL", "value": 19.363027}, "LTC": {"code": "LTC", "value": 0.011157}, "LTL": {"code": "LTL", "value": 3.129388}, "LVL": {"code": "LVL", "value": 0.641078}, "LYD": {"code": "LYD", "value": 5.105424}, "MAD": {"code": "MAD", "value": 11.016457}, "MATIC": {"code": "MATIC", "value": 0.781837}, "MDL": {"code": "MDL", "value": 19.920876}, "MGA": {"code": "MGA", "value": 4558.492716}, "MKD": {"code": "MKD", "value": 61.62819}, "MMK": {"code": "MMK", "value": 2225.205413}, "MNT": {"code": "MNT", "value": 3732.329033}, "MOP": {"code": "MOP", "value": 8.563169}, "MRO": {"code": "MRO", "value": 378.357343}, "MUR": {"code": "MUR", "value": 48.900402}, "MVR": {"code": "MVR", "value": 16.268336}, "MWK": {"code": "MWK", "value": 1088.323158}, "MXN": {"code": "MXN", "value": 19.470822}, "MYR": {"code": "MYR", "value": 4.699269}, "MZN": {"code": "MZN", "value": 66.875072}, "NAD": {"code": "NAD", "value": 19.363038}, "NGN": {"code": "NGN", "value": 487.98678}, "NIO": {"code": "NIO", "value": 38.718378}, "NOK": {"code": "NOK", "value": 10.922972}, "NPR": {"code": "NPR", "value": 140.251278}, "NZD": {"code": "NZD", "value": 1.700805}, "OMR": {"code": "OMR", "value": 0.40804}, "PAB": {"code": "PAB", "value": 1.059592}, "PEN": {"code": "PEN", "value": 4.033816}, "PGK": {"code": "PGK", "value": 3.781705}, "PHP": {"code": "PHP", "value": 58.258677}, "PKR": {"code": "PKR", "value": 276.561187}, "PLN": {"code": "PLN", "value": 4.728053}, "PYG": {"code": "PYG", "value": 7746.773115}, "QAR": {"code": "QAR", "value": 3.858827}, "RON": {"code": "RON", "value": 4.916219}, "RSD": {"code": "RSD", "value": 117.312237}, "RUB": {"code": "RUB", "value": 79.910898}, "RWF": {"code": "RWF", "value": 1153.067355}, "SAR": {"code": "SAR", "value": 3.976542}, "SBD": {"code": "SBD", "value": 8.761292}, "SCR": {"code": "SCR", "value": 14.720557}, "SDG": {"code": "SDG", "value": 622.648002}, "SEK": {"code": "SEK", "value": 11.054627}, "SGD": {"code": "SGD", "value": 1.42313}, "SHP": {"code": "SHP", "value": 1.289544}, "SLL": {"code": "SLL", "value": 20931.581454}, "SOL": {"code": "SOL", "value": 0.044293}, "SOS": {"code": "SOS", "value": 602.511296}, "SRD": {"code": "SRD", "value": 35.472382}, "STD": {"code": "STD", "value": 21936.237757}, "SVC": {"code": "SVC", "value": 9.272143}, "SYP": {"code": "SYP", "value": 2662.848651}, "SZL": {"code": "SZL", "value": 19.404356}, "THB": {"code": "THB", "value": 36.786589}, "TJS": {"code": "TJS", "value": 11.565746}, "TMT": {"code": "TMT", "value": 3.719992}, "TND": {"code": "TND", "value": 3.341105}, "TOP": {"code": "TOP", "value": 2.491811}, "TRY": {"code": "TRY", "value": 20.002522}, "TTD": {"code": "TTD", "value": 7.196411}, "TWD": {"code": "TWD", "value": 32.102693}, "TZS": {"code": "TZS", "value": 2471.515284}, "UAH": {"code": "UAH", "value": 38.942628}, "UGX": {"code": "UGX", "value": 3946.988787}, "USD": {"code": "USD", "value": 1.059825}, "UYU": {"code": "UYU", "value": 41.658235}, "UZS": {"code": "UZS", "value": 11991.680672}, "VEF": {"code": "VEF", "value": 2579256.247536}, "VND": {"code": "VND", "value": 25255.679857}, "VUV": {"code": "VUV", "value": 125.922652}, "WST": {"code": "WST", "value": 2.878335}, "XAF": {"code": "XAF", "value": 655.472502}, "XAG": {"code": "XAG", "value": 0.049687}, "XAU": {"code": "XAU", "value": 0.000581}, "XCD": {"code": "XCD", "value": 2.864235}, "XDR": {"code": "XDR", "value": 0.795312}, "XOF": {"code": "XOF", "value": 655.472596}, "XPF": {"code": "XPF", "value": 118.96553}, "XRP": {"code": "XRP", "value": 2.718029}, "YER": {"code": "YER", "value": 265.327565}, "ZAR": {"code": "ZAR", "value": 19.31052}, "ZMK": {"code": "ZMK", "value": 9539.696805}, "ZMW": {"code": "ZMW", "value": 20.847607}, "ZWL": {"code": "ZWL", "value": 341.263218}}}